<?xml version="1.0" encoding="UTF-8" ?>
<meishi>
<item>
<name>传统韭菜盒</name>
<intro>传统韭菜盒</intro>
<pricesweb>Null</pricesweb>
<prices>0</prices>
<link>http://www.yctravel.com/tuangou/meishishow.asp?id=135</link>
<Pic_Address>http://zy.yctravel.com/UpFiles/Pic_Files/Small_Pic/20140422/20140422111947644764.jpg</Pic_Address>
<addtime>2014/4/22 11:19:43</addtime>
</item>
<item>
<name>铁板黑胶驴肉</name>
<intro>铁板黑胶驴肉</intro>
<pricesweb>Null</pricesweb>
<prices>0</prices>
<link>http://www.yctravel.com/tuangou/meishishow.asp?id=134</link>
<Pic_Address>http://zy.yctravel.com/UpFiles/Pic_Files/Small_Pic/20140422/20140422111828922892.jpg</Pic_Address>
<addtime>2014/4/22 11:18:43</addtime>
</item>
<item>
<name>假日水晶粉</name>
<intro>假日水晶粉</intro>
<pricesweb>Null</pricesweb>
<prices>0</prices>
<link>http://www.yctravel.com/tuangou/meishishow.asp?id=133</link>
<Pic_Address>http://zy.yctravel.com/UpFiles/Pic_Files/Small_Pic/20140422/20140422111743064306.jpg</Pic_Address>
<addtime>2014/4/22 11:17:33</addtime>
</item>
<item>
<name>野地三鲜</name>
<intro>野地三鲜</intro>
<pricesweb>Null</pricesweb>
<prices>0</prices>
<link>http://www.yctravel.com/tuangou/meishishow.asp?id=132</link>
<Pic_Address>http://zy.yctravel.com/UpFiles/Pic_Files/Small_Pic/20140422/20140422111533953395.jpg</Pic_Address>
<addtime>2014/4/22 11:15:40</addtime>
</item>
<item>
<name>清明果</name>
<intro>清明果</intro>
<pricesweb>Null</pricesweb>
<prices>0</prices>
<link>http://www.yctravel.com/tuangou/meishishow.asp?id=131</link>
<Pic_Address>http://zy.yctravel.com/UpFiles/Pic_Files/Small_Pic/20140422/20140422111442084208.jpg</Pic_Address>
<addtime>2014/4/22 11:14:49</addtime>
</item>
<item>
<name>粗粮天麻鸭</name>
<intro>粗粮天麻鸭</intro>
<pricesweb>Null</pricesweb>
<prices>0</prices>
<link>http://www.yctravel.com/tuangou/meishishow.asp?id=130</link>
<Pic_Address>http://zy.yctravel.com/UpFiles/Pic_Files/Small_Pic/20140422/20140422110855175517.jpg</Pic_Address>
<addtime>2014/4/22 11:08:48</addtime>
</item>
<item>
<name>金牌烤乳猪</name>
<intro>金牌烤乳猪</intro>
<pricesweb>Null</pricesweb>
<prices>0</prices>
<link>http://www.yctravel.com/tuangou/meishishow.asp?id=129</link>
<Pic_Address>http://zy.yctravel.com/UpFiles/Pic_Files/Small_Pic/20140422/20140422110511321132.jpg</Pic_Address>
<addtime>2014/4/22 11:05:34</addtime>
</item>
<item>
<name>奉新米糖</name>
<intro>用米浆、姜片与麦芽制成。 
先把稀释后的米浆与姜片
置于锅里烧滚几下，灭火后，
再加入舂碎的麦芽进行发酵。
再倒入特制的木框中晾干成型，
用菜刀切成小块状即可食用。</intro>
<pricesweb>Null</pricesweb>
<prices>12</prices>
<link>http://www.yctravel.com/tuangou/meishishow.asp?id=128</link>
<Pic_Address>http://zy.yctravel.com/UpFiles/Pic_Files/Small_Pic/20140417/20140417111794119411.jpg</Pic_Address>
<addtime>2014/4/17 11:17:18</addtime>
</item>
<item>
<name>奉新米粉</name>
<intro>


大米水磨成浆，锅烫成薄片，
 切成丝，入汤煮熟，
佐以精肉丝、香菇丝，
面皮厚薄均匀，切条工整，汤味鲜美。</intro>
<pricesweb>Null</pricesweb>
<prices>8</prices>
<link>http://www.yctravel.com/tuangou/meishishow.asp?id=127</link>
<Pic_Address>http://zy.yctravel.com/UpFiles/Pic_Files/Small_Pic/20140417/20140417111091769176.jpg</Pic_Address>
<addtime>2014/4/17 11:11:19</addtime>
</item>
<item>
<name>神仙草（学名：平卧菊三七）菜谱</name>
<intro>1988年世界人文组织在印度尼西亚考察，在一个小岛上，他们惊奇地发现，岛上有一半以上的都是百岁老人，科学家对当地的土质、水质、空气、温度做了深入的调查和研究后发现，这些百岁老人经常使用一种名叫神仙草(学名：平卧菊三七)的植物，他们会经常把神仙草的根部泡茶喝，叶子当菜食用。得到这一惊奇的发现之后，中国科学家对神仙草做了研究。根据研究表明，这种植物能抗流感病毒，对抑制乙肝、降血糖、降血压等有着显著的功效，还具有提高人体免疫力之作用，同时，它还是一种药食兼用的保健养生植物。卫生部2012年第8号公告允许平卧菊三七为普通食品。从此，神仙草作为一种特色蔬菜可以放心走进老百姓的日常生活中。




</intro>
<pricesweb>Null</pricesweb>
<prices>0</prices>
<link>http://www.yctravel.com/tuangou/meishishow.asp?id=126</link>
<Pic_Address>http://zy.yctravel.com/UpFiles/Pic_Files/Small_Pic/20131107/20131107160896249624.bmp</Pic_Address>
<addtime>2013/11/7 16:13:01</addtime>
</item>
<item>
<name>小炒苦栗干</name>
<intro>靖安主要特产之—苦栗干 苦栗干采用高山天然野果苦栗子为原料。加工而成，营养丰富。取消化，降血脂，调节血压，减肥等作用。食用时将苦栗子干，用开水浸泡后，（也可以放入锅内沸水中煮至完全软化后）捞起用冷水浇淋之后，可煮可炒，食用柔软爽口，别有风味
</intro>
<pricesweb>Null</pricesweb>
<prices>0</prices>
<link>http://www.yctravel.com/tuangou/meishishow.asp?id=125</link>
<Pic_Address>http://zy.yctravel.com/UpFiles/Pic_Files/Small_Pic/20131009/20131009163611201120.jpg</Pic_Address>
<addtime>2013/10/9 16:39:43</addtime>
</item>
<item>
<name>农家红烧肉</name>
<intro>靖安红烧肉和别的地方不同。农村办酒席都是用大铁锅自家养的过年猪（自己养的自己吃，不会喂养饲料）味道绝对鲜美。。。
</intro>
<pricesweb>Null</pricesweb>
<prices>0</prices>
<link>http://www.yctravel.com/tuangou/meishishow.asp?id=124</link>
<Pic_Address>http://zy.yctravel.com/UpFiles/Pic_Files/Small_Pic/20131009/20131009162949374937.jpg</Pic_Address>
<addtime>2013/10/9 16:34:29</addtime>
</item>
<item>
<name>糯米排骨</name>
<intro>靖安美食之二（糯米排骨）采用靖安高山客家糯和农家猪排秘制而成。，，
</intro>
<pricesweb>Null</pricesweb>
<prices>0</prices>
<link>http://www.yctravel.com/tuangou/meishishow.asp?id=123</link>
<Pic_Address>http://zy.yctravel.com/UpFiles/Pic_Files/Small_Pic/20131009/20131009162779767976.jpg</Pic_Address>
<addtime>2013/10/9 16:31:02</addtime>
</item>
<item>
<name>芋头圆子</name>
<intro>靖安美食之一（芋头圆子）用靖安特产高山芋头和本地产的红薯粉制作而成。

</intro>
<pricesweb>Null</pricesweb>
<prices>0</prices>
<link>http://www.yctravel.com/tuangou/meishishow.asp?id=122</link>
<Pic_Address>http://zy.yctravel.com/UpFiles/Pic_Files/Small_Pic/20131009/20131009161992139213.jpg</Pic_Address>
<addtime>2013/10/9 16:24:17</addtime>
</item>
<item>
<name>靖安啤酒烤鸭</name>
<intro>采用靖安本地鸭加啤酒烤制。（特别注明一定要到靖安青湖菜市场门口，对面有个水果摊的。那家才是正宗的）他采用台湾技术加上本地鸭烤制而成。。。


</intro>
<pricesweb>Null</pricesweb>
<prices>0</prices>
<link>http://www.yctravel.com/tuangou/meishishow.asp?id=121</link>
<Pic_Address>http://zy.yctravel.com/UpFiles/Pic_Files/Small_Pic/20131009/20131009161814161416.jpg</Pic_Address>
<addtime>2013/10/9 16:22:01</addtime>
</item>
<item>
<name>糖醋排骨</name>
<intro>靖安味（糖醋排骨）这道菜没过多的配料，最重要的就是糖醋的比例买质量好的肋排，而不是普通的排骨。（是采用靖安农家潲水，谷糠，野菜喂养的猪排
</intro>
<pricesweb>Null</pricesweb>
<prices>0</prices>
<link>http://www.yctravel.com/tuangou/meishishow.asp?id=120</link>
<Pic_Address>http://zy.yctravel.com/UpFiles/Pic_Files/Small_Pic/20131009/2013100916160630630.jpg</Pic_Address>
<addtime>2013/10/9 16:20:19</addtime>
</item>
<item>
<name>西头鸡</name>
<intro>传说还有感人的故事哦！相传很多年前靖安高湖西头有个穷书生叫况钟，在外求学回家过年，途中风雪交加感染风寒，回家老母亲问他想吃什么东西，他说：“没味口。”然后老母亲把过年杀好的鸡与坛子里的酸椒、大蒜、米醋烧成一碗。当鸡烧好时散发出一股开胃的香味，顿时穷书生问老母亲烧的是什么菜，好香啊！老母亲添了一碗酸椒鸡汤，书生喝完时胃口大增说：“再来一碗”！当吃饱时满头大汗。第二天，书生的风寒好了，才想起昨天的酸椒鸡汤还能治风寒。三年后，穷书生况钟当官后仍然回味当年母亲的酸辣鸡，但此时母亲已不在，为了纪念母亲、怀念家乡故将此酸辣鸡取名为“西头土鸡”也叫“过年鸡”。
</intro>
<pricesweb>Null</pricesweb>
<prices>0</prices>
<link>http://www.yctravel.com/tuangou/meishishow.asp?id=119</link>
<Pic_Address>http://zy.yctravel.com/UpFiles/Pic_Files/Small_Pic/20131009/20131009161542784278.jpg</Pic_Address>
<addtime>2013/10/9 16:19:06</addtime>
</item>
<item>
<name>土杂粉</name>
<intro>手工艺做的哦，亲。。。这可是靖安人的灵魂啊！！！不管走到哪里。身在何方，这碗粉让靖安人牵肠挂肚。。。（绝大部分在外的靖安游子到家的第一件事就是吃这碗粉
</intro>
<pricesweb>Null</pricesweb>
<prices>0</prices>
<link>http://www.yctravel.com/tuangou/meishishow.asp?id=118</link>
<Pic_Address>http://zy.yctravel.com/UpFiles/Pic_Files/Small_Pic/20131009/20131009161211441144.jpg</Pic_Address>
<addtime>2013/10/9 16:16:19</addtime>
</item>
<item>
<name>农家鲜辣水煮鸭</name>
<intro>靖安菜和其他赣菜差不多。鲜辣。水煮鸭三件足够辣，吃到一身汗是没啥问题，尽管开了空调
</intro>
<pricesweb>Null</pricesweb>
<prices>0</prices>
<link>http://www.yctravel.com/tuangou/meishishow.asp?id=117</link>
<Pic_Address>http://zy.yctravel.com/UpFiles/Pic_Files/Small_Pic/20131009/20131009161161596159.jpg</Pic_Address>
<addtime>2013/10/9 16:15:01</addtime>
</item>
<item>
<name>干锅腐竹</name>
<intro>江西的腐竹是久煮不烂的，但靖安做的腐竹特别的好吃，在泡发腐竹的时候有时间的话用冷水，会更加的韧性，如果时间比较急的话直接用热水泡发，这样也不会碎掉，只是口感软一点。这道菜可以不放辣椒，按照口味而定，猪油的味道和清鸡汤完全把腐竹演绎的很完美。。。。
</intro>
<pricesweb>Null</pricesweb>
<prices>0</prices>
<link>http://www.yctravel.com/tuangou/meishishow.asp?id=116</link>
<Pic_Address>http://zy.yctravel.com/UpFiles/Pic_Files/Small_Pic/20131009/20131009160885428542.jpg</Pic_Address>
<addtime>2013/10/9 16:13:57</addtime>
</item>
<item>
<name>大碗菜</name>
<intro>靖安，朴实的农家人喜欢用大碗装菜，他们用最简单的调味料做出了各种各样风味独特的大碗菜，香味十足，吃起来非常过瘾。最受欢迎的有大碗花菜、大碗香干、大碗长豆角、大碗莲藕等。因为农家乐的推广，农家菜也渐渐走上大家的餐桌了。正宗与否我不敢保证，但是按照自家人的喜好来做，每次留下的空碗就是对我们靖安美食最好的肯定哈！五花肉鲜香，莲藕脆嫩，非常可口的下饭菜，值得试试哦
</intro>
<pricesweb>Null</pricesweb>
<prices>0</prices>
<link>http://www.yctravel.com/tuangou/meishishow.asp?id=115</link>
<Pic_Address>http://zy.yctravel.com/UpFiles/Pic_Files/Small_Pic/20131009/20131009160728542854.jpg</Pic_Address>
<addtime>2013/10/9 16:11:08</addtime>
</item>
<item>
<name>客家杀猪菜</name>
<intro>靖安客家散养猪。用肥猪肉、猪大肠、猪血旺、猪肝、白豆腐切成片，酸菜切成段，姜切丝，葱切成葱花。杀猪菜，原本是靖安农村每年接近年关杀年猪时所吃的一种炖菜。过去，人们没有条件讲究什么配料、调料，只是把刚杀好的猪的血脖子斩成大块煮熟后切成大片放进锅里，然后边煮边往里面放以经处理好的干白菜。加水和调料，等到肉烂菜熟后，再把灌好的血肠倒进锅内煮熟。上菜时，一盘肉，一盘酸菜，一盘血肠，也有的是把三者合一。这种菜不是刚做的好吃。而是多做。以后吃的时候一热。那才是最好吃的。亲，不错哦。。。
</intro>
<pricesweb>Null</pricesweb>
<prices>0</prices>
<link>http://www.yctravel.com/tuangou/meishishow.asp?id=114</link>
<Pic_Address>http://zy.yctravel.com/UpFiles/Pic_Files/Small_Pic/20131009/20131009160496029602.jpg</Pic_Address>
<addtime>2013/10/9 16:08:37</addtime>
</item>
<item>
<name>冷水鱼</name>
<intro>来自靖安小湾水库和罗湾水库（冷水鱼）鳜鱼`鳙鱼等各种鱼各种做法。。。。。。（冷水鱼。注解：高山流下来无污染的泉水长年水温较低，鱼生长在高山冷水中，更鲜美

</intro>
<pricesweb>Null</pricesweb>
<prices>0</prices>
<link>http://www.yctravel.com/tuangou/meishishow.asp?id=113</link>
<Pic_Address>http://zy.yctravel.com/UpFiles/Pic_Files/Small_Pic/20131009/20131009160246004600.jpg</Pic_Address>
<addtime>2013/10/9 16:06:45</addtime>
</item>
<item>
<name>烧酒醉虾</name>
<intro>采用靖安北河鲜之一“小草虾”。。。小草醉虾一定要活的虾会在碗里跳，只见虾体上下跳动，盖子被撞得砰砰作响，剔透玲珑的身段，醉态可掬的模样让人实在不忍下之毒手。客人一个个吃得香的很。
最近总有买到好鲜活的虾，煮的，炒的，煎的，烧的统统吃腻了，何不来个醉虾尝尝鲜
</intro>
<pricesweb>Null</pricesweb>
<prices>0</prices>
<link>http://www.yctravel.com/tuangou/meishishow.asp?id=112</link>
<Pic_Address>http://zy.yctravel.com/UpFiles/Pic_Files/Small_Pic/20131009/20131009155976357635.jpg</Pic_Address>
<addtime>2013/10/9 16:03:25</addtime>
</item>
<item>
<name>牛骨浓汤</name>
<intro>采用靖安高山散养黄牛骨长时间熬制。。味道鲜美，深受各界人士的青睐。牛骨头！骨汁、骨油、骨膜、骨肉、美味烹调至最佳状态，使其香味独特、营养丰富，让人吃了还想吃，回味深长！
</intro>
<pricesweb>Null</pricesweb>
<prices>0</prices>
<link>http://www.yctravel.com/tuangou/meishishow.asp?id=111</link>
<Pic_Address>http://zy.yctravel.com/UpFiles/Pic_Files/Small_Pic/20131009/20131009155771037103.jpg</Pic_Address>
<addtime>2013/10/9 12:02:07</addtime>
</item>
<item>
<name>禾堆饼</name>
<intro>

做法：浸米/磨米粉/溲团/揉饼/上色/蒸饼/堆饼。像征着“五谷丰登，一年胜一年”。</intro>
<pricesweb>Null</pricesweb>
<prices>0</prices>
<link>http://www.yctravel.com/tuangou/meishishow.asp?id=110</link>
<Pic_Address>http://zy.yctravel.com/UpFiles/Pic_Files/Small_Pic/20130704/20130704102928552855.jpg</Pic_Address>
<addtime>2013/7/4 10:32:42</addtime>
</item>
<item>
<name>客家点心</name>
<intro>
热情迎客

甜甜蜜蜜

年年有鱼

多子多福
靖安客家人约占全县人口的三分之一,主要分布于山上片.客家人用家种与野生售票自制风味点心和食品待客.有茄子干 、苦瓜干、姜片等；用果子晒的有杨桃干、木瓜干、杨梅干等；用糖食加工的有油果子、炒米糖、灰水米果等。客家点心制作要求选料精、工艺巧、造型美、色香味俱佳。</intro>
<pricesweb>Null</pricesweb>
<prices>0</prices>
<link>http://www.yctravel.com/tuangou/meishishow.asp?id=109</link>
<Pic_Address>http://zy.yctravel.com/UpFiles/Pic_Files/Small_Pic/20130704/20130704101894639463.jpg</Pic_Address>
<addtime>2013/7/4 10:27:41</addtime>
</item>
<item>
<name>七叶饼</name>
<intro>
做法:黄豆叶、葫芦叶、豆角叶和糯米一起碾碎，做成薄饼，蒸熟即可.</intro>
<pricesweb>Null</pricesweb>
<prices>0</prices>
<link>http://www.yctravel.com/tuangou/meishishow.asp?id=108</link>
<Pic_Address>http://zy.yctravel.com/UpFiles/Pic_Files/Small_Pic/20130704/2013070410120238238.jpg</Pic_Address>
<addtime>2013/7/4 10:13:51</addtime>
</item>
<item>
<name>黄元米果</name>
<intro>
做法:将黄元糯米洗净浸胀，用大木甑蒸熟，拌入黄元柴烧灰而制成的碱水，第二天分批用小甑复蒸后倒入石臼，由数人用木碓和木棍，伴随劳动号子将其捣烂，最后搓成条状后，做成米饼，再用木模印上带有吉祥的图案,该果品呈金黄色柔韧温香，是客家人主要风味食品，在正月初一与青菜共同煮食.</intro>
<pricesweb>Null</pricesweb>
<prices>0</prices>
<link>http://www.yctravel.com/tuangou/meishishow.asp?id=107</link>
<Pic_Address>http://zy.yctravel.com/UpFiles/Pic_Files/Small_Pic/20130704/20130704100813491349.jpg</Pic_Address>
<addtime>2013/7/4 10:11:23</addtime>
</item>
<item>
<name>神仙菜</name>
<intro>
做法:用油淋，清炒,降血压、血脂</intro>
<pricesweb>Null</pricesweb>
<prices>0</prices>
<link>http://www.yctravel.com/tuangou/meishishow.asp?id=106</link>
<Pic_Address>http://zy.yctravel.com/UpFiles/Pic_Files/Small_Pic/20130704/20130704100366686668.jpg</Pic_Address>
<addtime>2013/7/4 10:05:05</addtime>
</item>
<item>
<name>艾饼</name>
<intro>
做法:祀祖宗在清明，艾叶炒糯搓成团，甜不腻来肥不膄,选二叶一心的艾叶经沸水炀一分钟后与糯米粉搓成团，腊肉春笋切丁炒熟裹入上笼蒸即食.</intro>
<pricesweb>Null</pricesweb>
<prices>0</prices>
<link>http://www.yctravel.com/tuangou/meishishow.asp?id=105</link>
<Pic_Address>http://zy.yctravel.com/UpFiles/Pic_Files/Small_Pic/20130704/20130704095452005200.jpg</Pic_Address>
<addtime>2013/7/4 10:01:32</addtime>
</item>
<item>
<name>稻叶米果</name>
<intro>
做法:禾子米洗净浸胀，把稻叶切碎拌入米中，加少量盐，将米机成粉，待水烧开后，用开水把机成的粉和成米团，做成汤圆状，放入木甑蒸半小时为宜，取出即可,可以蒸吃，孕妇不能食用.
</intro>
<pricesweb>Null</pricesweb>
<prices>0</prices>
<link>http://www.yctravel.com/tuangou/meishishow.asp?id=104</link>
<Pic_Address>http://zy.yctravel.com/UpFiles/Pic_Files/Small_Pic/20130704/20130704094859425942.jpg</Pic_Address>
<addtime>2013/7/4 9:50:31</addtime>
</item>
<item>
<name>清炒苦菜</name>
<intro>
做法:锅中入油，油热倒入鸡蛋液摊开转小火，用锅铲划散鸡蛋，倒入黄花菜一同翻炒加少水
加盐、少糖，滴一点麻油，撒入葱花，盖上锅子一会会就可以起锅了,具有清热排毒的功效.</intro>
<pricesweb>Null</pricesweb>
<prices>0</prices>
<link>http://www.yctravel.com/tuangou/meishishow.asp?id=103</link>
<Pic_Address>http://zy.yctravel.com/UpFiles/Pic_Files/Small_Pic/20130704/20130704094149234923.jpg</Pic_Address>
<addtime>2013/7/4 9:46:47</addtime>
</item>
<item>
<name>春卷</name>
<intro>
由来:立春有吃春卷“咬春”的习俗，寓意新年初始“有头有尾
做法:用干面皮包馅心，经煎、炸而成</intro>
<pricesweb>Null</pricesweb>
<prices>0</prices>
<link>http://www.yctravel.com/tuangou/meishishow.asp?id=102</link>
<Pic_Address>http://zy.yctravel.com/UpFiles/Pic_Files/Small_Pic/20130704/20130704094078367836.jpg</Pic_Address>
<addtime>2013/7/4 9:23:56</addtime>
</item>
<item>
<name>袁州松花皮蛋</name>
<intro>　 皮蛋处处有出产，风味还数袁州好。袁州松花皮蛋，配料精当，加工讲究，操作严格，风味独特。 
　　对袁州松花皮蛋的吃法，应观其色、品其味，适宜慢慢品尝，不宜囫囵吞枣。松花皮蛋是一种色香味俱全的制成品，慢慢品味简直是一种艺术享受。
　　先看外观，松花皮蛋去壳后，可见蛋白晶莹透明，富弹性，呈深蓝或豆黄色泽，表面有形象各异的松花图案，煞是好看。剖开则蛋白蛋黄层次分明。蛋黄凝而不固，切面可见同心轮状，由内而外呈现蓝、豆黄、灰黑、茶青五层深浅不一的色彩。故袁州松花皮蛋又称为“五彩松花皮蛋”。其中，蛋黄略稀凝而不流的，称为“溏心松花皮蛋”，而蛋黄色彩较深、凝固而有弹性的，称为“硬心松花皮蛋”。
　　皮蛋可一切为二或一切为四，装盘时整齐排列，十分好看。有的厨师做工精细，将皮蛋用嫩线横切成圆片，再依次装盘上席，光亮的色彩，生动的花纹，令你不忍下箸。
　　袁州松花皮蛋，吃起来有质地柔嫩、清凉可口、味美香淡之感，据称有清火驱热、化痰生津的功效，因此，是很好的下酒菜。

</intro>
<pricesweb>Null</pricesweb>
<prices>30</prices>
<link>http://www.yctravel.com/tuangou/meishishow.asp?id=3</link>
<Pic_Address>http://zy.yctravel.com/UpFiles/Pic_Files/Small_Pic/20110322/20110322160087308730.jpg</Pic_Address>
<addtime>2013/5/8 18:04:28</addtime>
</item>
<item>
<name>包圆</name>
<intro>铜鼓客家人特有的食品，也是招待贵宾的佳肴。做法与饺子相似，但馅心很讲究，由精制瘦肉、冬笋、香菇、鸡肉、莲子及各种调味品组成。外皮是由芋子去皮加红薯粉揉和发韧而成。包圆的形状可以随心所欲，有圆形、半圆形、三角形及各种动物形。经旺火蒸熟后，鲜香可口、甜味甘肥、软而不粘、晶莹松韧，使人食而不忘，回味无穷。铜鼓“包圆”多为三角形，蕴寓着客这人爱国爱乡的优良传统。三角形的“三角”分别代表铜鼓客家人根在中原，情系中原；来自闽粤赣，情系闽粤赣；扎根赣西北、情系赣西北这三种寓意。</intro>
<pricesweb>Null</pricesweb>
<prices>28</prices>
<link>http://www.yctravel.com/tuangou/meishishow.asp?id=7</link>
<Pic_Address>http://zy.yctravel.com/UpFiles/Pic_Files/Small_Pic/20110301/20110301104743964396.jpg</Pic_Address>
<addtime>2013/5/8 18:04:28</addtime>
</item>
<item>
<name>宜春慈化鸡 </name>
<intro>相传很多年前慈化镇有个穷书生，在外求学回家过年，途中风雪交加感染风寒，回家老母亲问他想吃什么东西，他说：“没味口。”然后老母亲把过年杀好的鸡与坛子里的酸椒、大蒜、米醋烧成一碗。当鸡烧好时散发出一股开胃的香味，顿时穷书生问老母亲烧的是什么菜，好香啊！老母亲添了一碗酸椒鸡汤，书生喝完时胃口大增说：“再来一碗”！当吃饱时满头大汗。第二天，书生的风寒好了，才想起昨天的酸椒鸡汤还能治风寒。三年后，穷书生当官后仍然回味当年母亲的酸辣鸡，但此时母亲已不在，为了纪念母亲、怀念家乡故将此酸辣鸡取名为“慈化土鸡”也叫“过年鸡”。 </intro>
<pricesweb>Null</pricesweb>
<prices>0</prices>
<link>http://www.yctravel.com/tuangou/meishishow.asp?id=9</link>
<Pic_Address>http://zy.yctravel.com/UpFiles/Pic_Files/Small_Pic/20110322/20110322150593569356.jpg</Pic_Address>
<addtime>2013/5/8 18:04:28</addtime>
</item>
<item>
<name>明月山温泉豆腐 </name>
<intro>明月山温泉风景名胜区境内含有罕见的富硒温泉，距今已有2000多年的历史。水温常年保持在68OC—72OC。经国家地质矿产部和中华预防医学科学院环境卫生监督所实验分析，该温泉水质清澈，无色、无味、无嗅，内涵多种人体所必须的微量元素，如硒、偏硅酸、锂、锶、钙等。经临床应用表明，温汤硒温泉对心血管疾病、类风湿、关节炎等疾病均有一定疗效。中国中央电视台《科技博览》、《绿色空间》、《走遍中国》等节目均曾走进明月山进行拍摄。 </intro>
<pricesweb>Null</pricesweb>
<prices>0</prices>
<link>http://www.yctravel.com/tuangou/meishishow.asp?id=10</link>
<Pic_Address>http://zy.yctravel.com/UpFiles/Pic_Files/Small_Pic/20110322/20110322150884718471.bmp</Pic_Address>
<addtime>2013/5/8 18:04:28</addtime>
</item>
<item>
<name>传统粉蒸肉 </name>
<intro>有一对恩爱夫妻，生活清贫安逸。丈夫立志发奋、寒窗苦读，妻子勤劳善良、温柔体贴。几年后，丈夫进京赶考，临行前，妻子连续三天三夜纺线织布，然后卖布买肉，当夜炒米磨粉，制做家乡米粉肉，送夫上路。谁知丈夫赴京科考，金榜题名，在外为官，数年不归。妻子思念丈夫，多次托人捎信要官人回家看看，当每次捎信都未能触动官人回乡之心。后来，妻子常常想起丈夫临行前的一幕，于是，不再托人捎信，而是请人送去一碗家乡米粉肉。 </intro>
<pricesweb>Null</pricesweb>
<prices>0</prices>
<link>http://www.yctravel.com/tuangou/meishishow.asp?id=11</link>
<Pic_Address>http://zy.yctravel.com/UpFiles/Pic_Files/Small_Pic/20110322/20110322151122282228.jpg</Pic_Address>
<addtime>2013/5/8 18:04:28</addtime>
</item>
<item>
<name>荷塘月色（鱼跃龙门）</name>
<intro>夏云姑在家中宴请张公公时，本来准备了母鸡与冬笋两道菜，不料将母鸡和冬笋一并煮了，这样就只有一道菜。她正在考虑如何做出第二道菜时，却无意听到张公公在念门口的春联，念到“家有余庆”时，云姑就笑了起来，心想正好就做一道鱼。于是准备出门抓鱼，刚走不远却不慎滑倒，起来时手里拿着一根土怀生。云姑心灵手巧，干脆就不去抓鱼，直接用这根怀生雕刻成鱼的形状做了一道菜，俗称云姑宴之二——水晶素鱼，后经改进传至现在。</intro>
<pricesweb>Null</pricesweb>
<prices>0</prices>
<link>http://www.yctravel.com/tuangou/meishishow.asp?id=12</link>
<Pic_Address>http://zy.yctravel.com/UpFiles/Pic_Files/Small_Pic/20110322/20110322151492339233.jpg</Pic_Address>
<addtime>2013/5/8 18:04:28</addtime>
</item>
<item>
<name>宜丰松肉</name>
<intro>据传在清乾隆年间，有个财主想显示自己大方，快过年了，于是请9位给他做事长工们吃饭，但又不想出破财，只给了厨娘5斤五花肉，厨娘拿到就想5斤肉怎么够长工们吃啊，正着急中，想起厨房碗柜中有包用剩的生粉，而灵机一动，就想何不将生粉与五花肉加以发挥，做一道菜呢！！说做就做，做好后，端于财主看，财主尝了尝，觉得此菜味道不错，有因肉色以金黄色为主，而冠名黄金肉。这样就创出一道流传后世的美味佳肴。解放后，政府认为黄金肉是劳动人民智慧创造，以黄金肉冠名太过富贵，又因此菜肉质酥软、味美、外型酷似松果而改名“松肉”。 </intro>
<pricesweb>Null</pricesweb>
<prices>0</prices>
<link>http://www.yctravel.com/tuangou/meishishow.asp?id=13</link>
<Pic_Address>http://zy.yctravel.com/UpFiles/Pic_Files/Small_Pic/20110322/20110322151986128612.jpg</Pic_Address>
<addtime>2013/5/8 18:04:28</addtime>
</item>
<item>
<name>葵花肉</name>
<intro>Null</intro>
<pricesweb>Null</pricesweb>
<prices>0</prices>
<link>http://www.yctravel.com/tuangou/meishishow.asp?id=14</link>
<Pic_Address>http://zy.yctravel.com/UpFiles/Pic_Files/Small_Pic/20110322/20110322152519521952.bmp</Pic_Address>
<addtime>2013/5/8 18:04:28</addtime>
</item>
<item>
<name>孔雀开屏（丹凤朝阳）——云姑宴之一 </name>
<intro>传说夏云姑（宋孝宗赵昚的成恭皇后）被张公公选中后请其至家中用餐。因家贫无好菜可用，为表示对张公公的感谢之情，将家中仅有的一只老母鸡杀了放在锅中煮。转身就去剥洗她在放鸭子时采的冬笋，刚好将冬笋洗好后就听到锅中冒气声。于是云姑便顺手拿着冬笋来揭开锅盖查看，却见锅中的母鸡抬头向云姑连点三下，云姑吓得将冬笋掉入锅中。无奈，只好将冬笋与母鸡一块烹煮，不料却十分可口，并传之后世，亦谓之云姑宴之一。</intro>
<pricesweb>Null</pricesweb>
<prices>0</prices>
<link>http://www.yctravel.com/tuangou/meishishow.asp?id=15</link>
<Pic_Address>http://zy.yctravel.com/UpFiles/Pic_Files/Small_Pic/20110322/20110322153193199319.jpg</Pic_Address>
<addtime>2013/5/8 18:04:28</addtime>
</item>
<item>
<name>汗蒸禅宗老笋干</name>
<intro>相传很多年前，有一个和尚，云游四海，有一天来到宜春的化成寺。当时化成寺的火夫，因拿不出好的斋菜，于是就将用水浸泡好的老笋干与茶油用隔水蒸的办法蒸好。当菜被端上桌时，和尚问火夫是如何制作的，火夫说：“用瓦罐隔水蒸的，该菜烹饪之前没有加水，但是菜成之后却有汤水。”方丈恍然大悟，原来此菜的汤汁全是水蒸汽。于是就为此菜取名为“汗蒸禅宗老笋干”。 </intro>
<pricesweb>Null</pricesweb>
<prices>0</prices>
<link>http://www.yctravel.com/tuangou/meishishow.asp?id=16</link>
<Pic_Address>http://zy.yctravel.com/UpFiles/Pic_Files/Small_Pic/20110322/20110322153385348534.jpg</Pic_Address>
<addtime>2013/5/8 18:04:28</addtime>
</item>
<item>
<name>铜鼓黑山羊</name>
<intro>相传明朝宰相严嵩特别喜欢吃羊肉。有一次他在返乡路过宜春的途中，听说当地铜鼓县深山有一种黑山羊，毛色纯黑、肉质细嫩、汤浓无腥，是当地官员接待朝廷高官的佳品。于是，严嵩要求当地知府命人烧制了一锅黑山羊肉，严嵩吃后赞不绝口，并专门把宜春的黑山羊带入京城进贡给皇帝。此后一举成名。 </intro>
<pricesweb>Null</pricesweb>
<prices>0</prices>
<link>http://www.yctravel.com/tuangou/meishishow.asp?id=17</link>
<Pic_Address>http://zy.yctravel.com/UpFiles/Pic_Files/Small_Pic/20110322/20110322153514221422.jpg</Pic_Address>
<addtime>2013/5/8 18:04:28</addtime>
</item>
<item>
<name>土家鱼</name>
<intro>Null</intro>
<pricesweb>Null</pricesweb>
<prices>0</prices>
<link>http://www.yctravel.com/tuangou/meishishow.asp?id=18</link>
<Pic_Address>http://zy.yctravel.com/UpFiles/Pic_Files/Small_Pic/20110322/20110322153740464046.jpg</Pic_Address>
<addtime>2013/5/8 18:04:28</addtime>
</item>
<item>
<name>海辉包圆</name>
<intro>几百年来，在客家人当中就流传着吃包圆，盼团圆的传统，用“包圆”款待尊贵的客人和团聚的亲人，或过年过节一道佳肴。客家人中主妇都会做包圆。绿色食品，具有保健功能；传统食品，口感独特，细腻，绵软；手工打造，回归自然,2003年获“中国名点”称号；十三届中国厨师节获制作金奖。</intro>
<pricesweb>Null</pricesweb>
<prices>0</prices>
<link>http://www.yctravel.com/tuangou/meishishow.asp?id=48</link>
<Pic_Address>http://zy.yctravel.com/UpFiles/Pic_Files/Small_Pic/20130205/20130205084156285628.JPG</Pic_Address>
<addtime>2013/5/8 18:04:28</addtime>
</item>
<item>
<name>竹笋</name>
<intro>纯天然野生，无任何污染，其味独特、清香脆嫩，内含丰富的氨基酸、维生素以及多种微量元素和大量的纤维素，是一种低脂肪、低热量的绿化食品。传统中医认为：竹笋性味甘，有滋阴补血、帮助消化之功效，经常食用绿色纤维，对促进人体消化、增加胃蠕动、减肥、降血糖、糖尿病等有明显的治疗和保健作用,是山珍中之极品。</intro>
<pricesweb>Null</pricesweb>
<prices>0</prices>
<link>http://www.yctravel.com/tuangou/meishishow.asp?id=54</link>
<Pic_Address>http://zy.yctravel.com/UpFiles/Pic_Files/Small_Pic/20130205/2013020508510805805.jpg</Pic_Address>
<addtime>2013/5/8 18:04:28</addtime>
</item>
<item>
<name>宜春扎粉</name>
<intro>在宜春，美味的小吃数不胜数。但是对于刚刚到这里的人来说，一定是迷茫的很，其实宜春与每个城市一样，所有的美味小吃都要自己去花心思来寻找，或者巧遇。一些老牌子的小吃店稳扎宜春很多年，真正的物美价廉，是逛街休闲的好去处；还有开了上十年的老字号饭馆，口味价格都很有良好的口碑。生活在宜春多年，多少对宜春的小吃美食有些了解。

宜春的扎粉、米面是一定要吃的。扎粉在有些省份也叫米粉，例如湖南、广西。近两年风行吃万载罗城的土扎粉，现在大小酒店都有这道主食，街头小摊或小餐馆的多以宜春自制的普通扎粉为多。炒扎粉配以小南瓜、肉丝、辣椒等佐料，有些也以青菜、豆芽、韭菜花等为佐料，最关键的一道佐料是料酒，料酒放的好，炒扎粉的味道自然就活了起来。
 很多广东人以为宜春的米面就是河粉，其实米面比河粉薄很多，柔软且又弹性。米面用篓子烫的最好吃，地道的篓子米面在宜春已经不太好找，即使有味道也差很多。现在大多是煮的，有些小店的煮米面味道很好，并且煮的很清爽的模样，这样的煮米面才能让食客食指大动，配上炒过的花生米，腌制的萝卜干，洒上一把细碎的葱花，保证吃一次就难忘。
 然后推荐一些有宜春特色菜式的店，可以在周末的时候邀三五好友边吃边聊，多了一些聚会的去处。
 宜春菜以辣为主，味道重，放很多样的配料来调味，不太能吃辣的人要慎重的考虑一下，以免伤及肠胃。比较著名的食街有两条，一条在体育中心旁边的正荣街，一条在潭前的美食街，两个地方大都是宜春菜，尤其适合夏天的晚上在店门口露天用餐。</intro>
<pricesweb>Null</pricesweb>
<prices>5</prices>
<link>http://www.yctravel.com/tuangou/meishishow.asp?id=84</link>
<Pic_Address>http://zy.yctravel.com/UpFiles/Pic_Files/Small_Pic/20130426/20130426153926892689.jpg</Pic_Address>
<addtime>2013/5/8 18:04:28</addtime>
</item>
<item>
<name>孙渡板鸭</name>
<intro>商品名称：板鸭
商品商标：孙渡
 商品特色说明:江西省传统特产,历史悠久,采用天然放养的优质麻鸭做原料，以精湛的传统工艺为基础，结合现代科学方法精制而成，其外形如月琴，表面光洁黄润，柔嫩古脆，香味诱人，素以“色、香、味、形”俱佳而称，是居家旅游，馈赠亲友之佳品。
 商品价格：
(1)批发价：20元/只
(2)零售价：28元/只
 生产企业:
(1)名 称:孙渡板鸭场
(2)地 址:孙渡街办
(3)联系人:谢平华：
(4)电 话:13707954473

</intro>
<pricesweb>Null</pricesweb>
<prices>28</prices>
<link>http://www.yctravel.com/tuangou/meishishow.asp?id=100</link>
<Pic_Address>http://zy.yctravel.com/UpFiles/Pic_Files/Small_Pic/20130507/20130507093625132513.jpg</Pic_Address>
<addtime>2013/5/8 18:04:28</addtime>
</item>
</meishi>
